inorbit_edge/__init__.py
inorbit_edge/commands.py
inorbit_edge/inorbit_pb2.py
inorbit_edge/metrics.py
inorbit_edge/missions.py
inorbit_edge/models.py
inorbit_edge/robot.py
inorbit_edge/types.py
inorbit_edge/utils.py
inorbit_edge/video.py
inorbit_edge-2.0.1.dist-info/licenses/LICENSE
inorbit_edge-2.0.1.dist-info/METADATA
inorbit_edge-2.0.1.dist-info/WHEEL
inorbit_edge-2.0.1.dist-info/top_level.txt
inorbit_edge-2.0.1.dist-info/RECORD
