Metadata-Version: 2.4
Name: inorbit-edge
Version: 2.0.1
Summary: InOrbit Edge SDK for Python
Home-page: https://github.com/inorbit-ai/edge-sdk-python
Download-URL: https://github.com/inorbit-ai/edge-sdk-python/archive/refs/tags/v2.0.1.zip
Author: InOrbit, Inc.
Author-email: support@inorbit.ai
Maintainer: Leandro Pineda
Maintainer-email: leandro@inorbit.ai
License: MIT
Project-URL: Tracker, https://inorbit.youtrack.cloud/issues/ESP/?q=State:%20-Resolved%20
Project-URL: Contributing, https://github.com/inorbit-ai/edge-sdk-python/blob/v2.0.1/CONTRIBUTING.md
Project-URL: Code of Conduct, https://github.com/inorbit-ai/edge-sdk-python/blob/v2.0.1/CODE_OF_CONDUCT.md
Project-URL: Changelog, https://github.com/inorbit-ai/edge-sdk-python/blob/v2.0.1/CHANGELOG.md
Project-URL: Issue Tracker, https://github.com/inorbit-ai/edge-sdk-python/issues
Project-URL: License, https://github.com/inorbit-ai/edge-sdk-python/blob/n2.0.1/LICENSE
Project-URL: About, https://www.inorbit.ai/company
Project-URL: Contact, https://www.inorbit.ai/contact
Project-URL: Blog, https://www.inorbit.ai/blog
Project-URL: Twitter, https://twitter.com/InOrbitAI
Project-URL: LinkedIn, https://www.linkedin.com/company/inorbitai
Project-URL: GitHub, https://github.com/inorbit-ai
Project-URL: Website, https://www.inorbit.ai/
Project-URL: Source, https://github.com/inorbit-ai/edge-sdk-python
Keywords: inorbit,robops,robotics
Platform: Linux
Platform: Mac OS-X
Platform: Windows
Classifier: Development Status :: 4 - Beta
Classifier: Intended Audience :: Developers
Classifier: License :: OSI Approved :: MIT License
Classifier: Natural Language :: English
Classifier: Operating System :: MacOS :: MacOS X
Classifier: Operating System :: Microsoft :: Windows
Classifier: Operating System :: POSIX :: Linux
Classifier: Programming Language :: Python :: 3.10
Classifier: Programming Language :: Python :: 3.11
Classifier: Programming Language :: Python :: 3.12
Classifier: Programming Language :: Python :: 3.13
Classifier: Topic :: Software Development :: Libraries :: Python Modules
Requires-Python: >=3.10, <3.14
License-File: LICENSE
Requires-Dist: requests<3.0,>=2.31
Requires-Dist: paho-mqtt<3.0,>=2.1.0
Requires-Dist: pillow<11.0,>=10.3
Requires-Dist: pyaml<24.0,>=23.12
Requires-Dist: pydantic<3.0,>=2.6
Requires-Dist: pysocks<2.0,>=1.7
Requires-Dist: protobuf<4.0,>=3.20
Requires-Dist: certifi>=2024.2
Requires-Dist: deprecated<2.0,>=1.2
Requires-Dist: rdp2~=1.1.2
Requires-Dist: opentelemetry-api~=1.39.1
Requires-Dist: opentelemetry-sdk~=1.39.1
Provides-Extra: video
Requires-Dist: opencv-python-headless<5.0,>=4.9; extra == "video"
Provides-Extra: dev
Requires-Dist: bump2version~=1.0; extra == "dev"
Requires-Dist: black<26.0,>=25.1; extra == "dev"
Requires-Dist: coverage~=7.6; extra == "dev"
Requires-Dist: flake8~=7.1; extra == "dev"
Requires-Dist: flake8-pyproject~=1.2; extra == "dev"
Requires-Dist: pip~=25.3; extra == "dev"
Requires-Dist: pytest~=8.4; extra == "dev"
Requires-Dist: pytest-mock~=3.14; extra == "dev"
Requires-Dist: requests-mock~=1.12; extra == "dev"
Requires-Dist: setuptools~=80.9; extra == "dev"
Requires-Dist: tox~=4.32; extra == "dev"
Requires-Dist: twine~=6.2; extra == "dev"
Requires-Dist: wheel~=0.45; extra == "dev"
Dynamic: author
Dynamic: author-email
Dynamic: classifier
Dynamic: description
Dynamic: description-content-type
Dynamic: download-url
Dynamic: home-page
Dynamic: keywords
Dynamic: license
Dynamic: license-file
Dynamic: maintainer
Dynamic: maintainer-email
Dynamic: platform
Dynamic: project-url
Dynamic: provides-extra
Dynamic: requires-dist
Dynamic: requires-python
Dynamic: summary
